randip/__init__.py
randip/cli.py
randip/gen.py
randip-0.1.0.dist-info/METADATA
randip-0.1.0.dist-info/WHEEL
randip-0.1.0.dist-info/entry_points.txt
randip-0.1.0.dist-info/RECORD
