Metadata-Version: 2.4
Name: randip
Version: 0.1.0
Summary: Random IP generator
Author: PICOPress
Requires-Python: >=3.10
